asynctnt-2.4.0.dist-info/RECORD
asynctnt-2.4.0.dist-info/WHEEL
asynctnt-2.4.0.dist-info/top_level.txt
asynctnt-2.4.0.dist-info/LICENSE.txt
asynctnt-2.4.0.dist-info/METADATA
asynctnt/instance.py
asynctnt/log.py
asynctnt/prepared.py
asynctnt/__init__.py
asynctnt/types.py
asynctnt/stream.py
asynctnt/api.py
asynctnt/connection.py
asynctnt/exceptions.py
asynctnt/iproto/schema.pxd
asynctnt/iproto/protocol.cpython-39-darwin.so
asynctnt/iproto/coreproto.pyx
asynctnt/iproto/protocol.pyx
asynctnt/iproto/rbuffer.pyx
asynctnt/iproto/db.pxd
asynctnt/iproto/buffer.pxd
asynctnt/iproto/__init__.py
asynctnt/iproto/const.pxi
asynctnt/iproto/unicodeutil.pxd
asynctnt/iproto/push.pxd
asynctnt/iproto/response.pyx
asynctnt/iproto/response.pxd
asynctnt/iproto/push.pyx
asynctnt/iproto/tarantool.pxd
asynctnt/iproto/bit.pxd
asynctnt/iproto/unicodeutil.pyx
asynctnt/iproto/buffer.pyx
asynctnt/iproto/db.pyx
asynctnt/iproto/protocol.pyi
asynctnt/iproto/rbuffer.pxd
asynctnt/iproto/xd.pxd
asynctnt/iproto/cmsgpuck.pxd
asynctnt/iproto/protocol.pxd
asynctnt/iproto/ttuple.pyx
asynctnt/iproto/coreproto.pxd
asynctnt/iproto/python.pxd
asynctnt/iproto/schema.pyx
asynctnt/iproto/ext/interval.pyx
asynctnt/iproto/ext/datetime.pyx
asynctnt/iproto/ext/decimal.pxd
asynctnt/iproto/ext/error.pxd
asynctnt/iproto/ext/uuid.pyx
asynctnt/iproto/ext/uuid.pxd
asynctnt/iproto/ext/error.pyx
asynctnt/iproto/ext/datetime.pxd
asynctnt/iproto/ext/decimal.pyx
asynctnt/iproto/ext/interval.pxd
asynctnt/iproto/tupleobj/__init__.pxd
asynctnt/iproto/requests/select.pxd
asynctnt/iproto/requests/eval.pyx
asynctnt/iproto/requests/auth.pyx
asynctnt/iproto/requests/update.pyx
asynctnt/iproto/requests/insert.pyx
asynctnt/iproto/requests/upsert.pxd
asynctnt/iproto/requests/prepare.pyx
asynctnt/iproto/requests/id.pxd
asynctnt/iproto/requests/streams.pyx
asynctnt/iproto/requests/ping.pxd
asynctnt/iproto/requests/base.pxd
asynctnt/iproto/requests/execute.pyx
asynctnt/iproto/requests/delete.pxd
asynctnt/iproto/requests/call.pxd
asynctnt/iproto/requests/delete.pyx
asynctnt/iproto/requests/call.pyx
asynctnt/iproto/requests/execute.pxd
