Metadata-Version: 2.1
Name: asynctnt
Version: 2.4.0
Summary: A fast Tarantool Database connector for Python/asyncio.
Author-email: igorcoding <igorcoding@gmail.com>
License: Apache License, Version 2.0
Project-URL: github, https://github.com/igorcoding/asynctnt
Classifier: Development Status :: 5 - Production/Stable
Classifier: Framework :: AsyncIO
Classifier: Operating System :: POSIX
Classifier: Operating System :: MacOS :: MacOS X
Classifier: Operating System :: Microsoft :: Windows
Classifier: Programming Language :: Python :: 3
Classifier: Programming Language :: Python :: 3 :: Only
Classifier: Programming Language :: Python :: 3.7
Classifier: Programming Language :: Python :: 3.8
Classifier: Programming Language :: Python :: 3.9
Classifier: Programming Language :: Python :: 3.10
Classifier: Programming Language :: Python :: 3.11
Classifier: Programming Language :: Python :: 3.12
Classifier: Programming Language :: Python :: Implementation :: CPython
Classifier: Intended Audience :: Developers
Classifier: License :: OSI Approved :: Apache Software License
Classifier: Topic :: Software Development :: Libraries :: Python Modules
Classifier: Topic :: Database :: Front-Ends
Requires-Python: >=3.7.0
License-File: LICENSE.txt
Requires-Dist: PyYAML>=5.0
Provides-Extra: docs
Requires-Dist: Sphinx>=5; extra == "docs"
Requires-Dist: sphinx-rtd-theme; extra == "docs"
Requires-Dist: sphinxcontrib-asyncio; extra == "docs"
Requires-Dist: myst-parser; extra == "docs"
Requires-Dist: sphinx-autodoc-typehints; extra == "docs"
Requires-Dist: sphinx-autoapi; extra == "docs"
Provides-Extra: test
Requires-Dist: isort; extra == "test"
Requires-Dist: black; extra == "test"
Requires-Dist: ruff; extra == "test"
Requires-Dist: pytest; extra == "test"
Requires-Dist: pytest-cov; extra == "test"
Requires-Dist: coverage[toml]; extra == "test"
Requires-Dist: pytz; extra == "test"
Requires-Dist: python-dateutil; extra == "test"
Requires-Dist: Cython==3.0.11; extra == "test"
Requires-Dist: uvloop>=0.12.3; (platform_system != "Windows" and platform_python_implementation != "PyPy") and extra == "test"
